more_itertools/__init__.py
more_itertools/__init__.pyi
more_itertools/more.py
more_itertools/more.pyi
more_itertools/py.typed
more_itertools/recipes.py
more_itertools/recipes.pyi
more_itertools-8.3.0.dist-info/LICENSE
more_itertools-8.3.0.dist-info/METADATA
more_itertools-8.3.0.dist-info/WHEEL
more_itertools-8.3.0.dist-info/top_level.txt
more_itertools-8.3.0.dist-info/RECORD
