Metadata-Version: 1.2
Name: more-itertools
Version: 8.3.0
Summary: More routines for operating on iterables, beyond itertools
Home-page: https://github.com/more-itertools/more-itertools
Author: Erik Rose
Author-email: erikrose@grinchcentral.com
License: MIT
Keywords: itertools,iterator,iteration,filter,peek,peekable,collate,chunk,chunked
Platform: UNKNOWN
Classifier: Development Status :: 5 - Production/Stable
Classifier: Intended Audience :: Developers
Classifier: Natural Language :: English
Classifier: License :: OSI Approved :: MIT License
Classifier: Programming Language :: Python :: 3
Classifier: Programming Language :: Python :: 3.5
Classifier: Programming Language :: Python :: 3.6
Classifier: Programming Language :: Python :: 3.7
Classifier: Programming Language :: Python :: 3.8
Classifier: Programming Language :: Python :: 3 :: Only
Classifier: Programming Language :: Python :: Implementation :: CPython
Classifier: Programming Language :: Python :: Implementation :: PyPy
Classifier: Topic :: Software Development :: Libraries
Requires-Python: >=3.5
